imap_easybox/__init__.py
imap_easybox/email.py
imap_easybox/folder.py
imap_easybox/server.py
imap_easybox/utils.py
imap_easybox-0.1.1.dist-info/LICENSE
imap_easybox-0.1.1.dist-info/METADATA
imap_easybox-0.1.1.dist-info/WHEEL
imap_easybox-0.1.1.dist-info/top_level.txt
imap_easybox-0.1.1.dist-info/RECORD
