Metadata-Version: 2.1
Name: imap-easybox
Version: 0.1.1
Summary: Easier use of imap mailboxes based on imaplib
Author-email: telecomshy <telecomshy@126.com>
License: MIT License
Project-URL: Homepage, https://github.com/telecomshy/imap-easybox
Keywords: imap,imaplib
Classifier: License :: OSI Approved :: MIT License
Classifier: Programming Language :: Python
Classifier: Programming Language :: Python :: 3
Requires-Python: >=3.7
License-File: LICENSE
Provides-Extra: dev
Requires-Dist: pytest ; extra == 'dev'
Requires-Dist: pip-tools ; extra == 'dev'
